advt/__init__.py
advt/attack/__init__.py
advt/attack/attack.py
advt/attack/bim.py
advt/attack/cw.py
advt/attack/deepfool.py
advt/attack/dim.py
advt/attack/fgsm.py
advt/attack/mim.py
advt/attack/sparseadv.py
advt/attack/universal.py
advt/benchmark/__init__.py
advt/benchmark/bim_cli.py
advt/benchmark/bit_depth_reduction_cli.py
advt/benchmark/comdefend_cli.py
advt/benchmark/cw_cli.py
advt/benchmark/cw_video_cli.py
advt/benchmark/deepfool_cli.py
advt/benchmark/dim_cli.py
advt/benchmark/fgsm_cli.py
advt/benchmark/fgsm_video_cli.py
advt/benchmark/mim_cli.py
advt/benchmark/mim_video_cli.py
advt/benchmark/randomization_cli.py
advt/benchmark/sparseadv_cli.py
advt/benchmark/tv_cli.py
advt/dataset/__init__.py
advt/dataset/hmdb51.py
advt/dataset/processor.py
advt/dataset/ucf101.py
advt/defence/__init__.py
advt/defence/bit_depth_reduction.py
advt/defence/comdefend.py
advt/defence/defence.py
advt/defence/randomization.py
advt/defence/total_variance_minimization.py
advt/model/__init__.py
advt/model/cnn.py
advt/model/cnn_rnn.py
advt/model/res18_test.py
advt/model/res18_train.py
advt/utils/__init__.py
advt/utils/img_process.py
advt/utils/metric.py
advt/utils/visualization.py
advt-1.0.3.dist-info/LICENSE
advt-1.0.3.dist-info/METADATA
advt-1.0.3.dist-info/WHEEL
advt-1.0.3.dist-info/top_level.txt
advt-1.0.3.dist-info/RECORD
