Metadata-Version: 2.1
Name: advt
Version: 1.0.3
Summary: A library for Attack & Defence on Video Task
Home-page: https://github.com/WindFantasy98/ADVT
Author: WindF98
Author-email: wwj98713@163.com
License: UNKNOWN
Platform: UNKNOWN
Classifier: Programming Language :: Python :: 3
Classifier: License :: OSI Approved :: MIT License
Classifier: Operating System :: Microsoft :: Windows :: Windows 10
Requires-Python: >=3.6
